presento/__init__.py
presento/reveal.js-master.zip
presento-0.3.0.dist-info/WHEEL
presento-0.3.0.dist-info/METADATA
presento-0.3.0.dist-info/RECORD
