Metadata-Version: 2.1
Name: presento
Version: 0.3.0
Summary: A tool to programmatically build slides using Reveal.js
License: MIT
Author-email: Jacopo Farina <jacopo1.farina@gmail.com>
Requires-Python: >=3.9
Requires-Dist: markdown>=3.4.1
Project-URL: Bug Tracker, https://github.com/jacopofar/presento/issues
Project-URL: Homepage, https://github.com/jacopofar/presento
